agentifyme/__init__.py
agentifyme/bootstrap.py
agentifyme/cache.py
agentifyme/client.py
agentifyme/errors.py
agentifyme/logger.py
agentifyme/prompt.py
agentifyme/py.typed
agentifyme/agents/__init__.py
agentifyme/components/__init__.py
agentifyme/components/base.py
agentifyme/components/reflection.py
agentifyme/components/task.py
agentifyme/components/utils.py
agentifyme/components/workflow.py
agentifyme/document_stores/__init__.py
agentifyme/document_stores/types.py
agentifyme/document_stores/vector/base.py
agentifyme/document_stores/vector/qdrant.py
agentifyme/ml/__init__.py
agentifyme/ml/embedding/__init__.py
agentifyme/ml/embedding/embeddings.py
agentifyme/ml/embedding/providers.py
agentifyme/ml/llm/__init__.py
agentifyme/ml/llm/anthropic.py
agentifyme/ml/llm/base.py
agentifyme/ml/llm/builder.py
agentifyme/ml/llm/cohere.py
agentifyme/ml/llm/groq.py
agentifyme/ml/llm/openai.py
agentifyme/tasks/__init__.py
agentifyme/tasks/json_data_extractor_task.py
agentifyme/tasks/structured_data_extractor_task.py
agentifyme/tools/__init__py
agentifyme/utilities/__init__.py
agentifyme/utilities/annotations.py
agentifyme/utilities/cli.py
agentifyme/utilities/env.py
agentifyme/utilities/func_utils.py
agentifyme/utilities/grpc.py
agentifyme/utilities/json_utils.py
agentifyme/utilities/meta.py
agentifyme/utilities/modules.py
agentifyme/utilities/time.py
agentifyme/worker/__init__.py
agentifyme/worker/callback.py
agentifyme/worker/context.py
agentifyme/worker/entrypoint.py
agentifyme/worker/helpers.py
agentifyme/worker/interceptor.py
agentifyme/worker/runtime.py
agentifyme/worker/worker_service.py
agentifyme/worker/workflows.py
agentifyme/worker/pb/api/v1/common_pb2.py
agentifyme/worker/pb/api/v1/common_pb2.pyi
agentifyme/worker/pb/api/v1/common_pb2_grpc.py
agentifyme/worker/pb/api/v1/gateway_pb2.py
agentifyme/worker/pb/api/v1/gateway_pb2.pyi
agentifyme/worker/pb/api/v1/gateway_pb2_grpc.py
agentifyme/worker/telemetry/__init__.py
agentifyme/worker/telemetry/base.py
agentifyme-0.2.11.dist-info/METADATA
agentifyme-0.2.11.dist-info/WHEEL
agentifyme-0.2.11.dist-info/entry_points.txt
agentifyme-0.2.11.dist-info/licenses/LICENSE
agentifyme-0.2.11.dist-info/RECORD
